stripe_kit/__init__.py
stripe_kit/asset.py
stripe_kit/env.py
stripe_kit/factory.py
stripe_kit/mesh.py
stripe_kit/scene_spec.py
stripe_kit/terrain.py
stripe_kit-0.3.0.dist-info/licenses/LICENSE
stripe_kit-0.3.0.dist-info/METADATA
stripe_kit-0.3.0.dist-info/WHEEL
stripe_kit-0.3.0.dist-info/top_level.txt
stripe_kit-0.3.0.dist-info/RECORD
