Metadata-Version: 2.4
Name: stripe_kit
Version: 0.3.0
Summary: Streamlined training for robots in plausible environments 
Author-email: Tomasz Chady <tomek.chady@gmail.com>, Jakub Markil <jakub.markil1@gmail.com>, Patryk Olszewski <patryk.olszewski@vip.onet.pl>, Oskar Winiarski <oskarwiniarski09@gmail.com>
License-Expression: GPL-3.0-only
Project-URL: Repository, https://github.com/GrafCzterech/STRIPE-kit
Classifier: Programming Language :: Python :: 3
Classifier: Operating System :: OS Independent
Classifier: Environment :: GPU :: NVIDIA CUDA
Classifier: Intended Audience :: Science/Research
Requires-Python: >=3.10
License-File: LICENSE
Requires-Dist: numpy
Provides-Extra: dev
Requires-Dist: black; extra == "dev"
Provides-Extra: docs
Requires-Dist: sphinx; extra == "docs"
Requires-Dist: sphinx-rtd-theme; extra == "docs"
Dynamic: license-file
